find_overlap/README.txt
find_overlap/__init__.py
find_overlap/__main__.py
gp_cmd_runr/README.txt
gp_cmd_runr/__init__.py
gp_cmd_runr/__main__.py
p_cmd_runr/Definitions.txt
p_cmd_runr/LICENSE.txt
p_cmd_runr/README.md
p_cmd_runr/__init__.py
p_cmd_runr/file_manip.py
p_cmd_runr/p_cmd_runr.py
p_cmd_runr/requirements.txt
p_cmd_runr-0.1.5.dist-info/LICENSE.txt
p_cmd_runr-0.1.5.dist-info/METADATA
p_cmd_runr-0.1.5.dist-info/WHEEL
p_cmd_runr-0.1.5.dist-info/entry_points.txt
p_cmd_runr-0.1.5.dist-info/top_level.txt
p_cmd_runr-0.1.5.dist-info/zip-safe
p_cmd_runr-0.1.5.dist-info/RECORD
