Metadata-Version: 2.1
Name: p_cmd_runr
Version: 0.1.5
Summary: A multi-purpose and flexible way to run commands on remote hosts.
Home-page: https://github.com/kaiyoux/p_cmd_runr
Author: Issa Lompo
Author-email: kaiyoux@gmail.com
Maintainer: Issa Lompo
Maintainer-email: kaiyoux@gmail.com
License: GNU General Public License v3 (GPLv3)
Project-URL: Bug Tracker, https://github.com/kaiyoux/p_cmd_runr/issues
Keywords: ssh,automation,automate,amos,moshell,remote,command,runner,run,execution,execute,paramiko,based,jumpbox,simple,easy,jump,hop
Classifier: Programming Language :: Python :: 3
Classifier: License :: OSI Approved :: GNU General Public License v3 (GPLv3)
Classifier: Operating System :: OS Independent
Classifier: Environment :: Console
Classifier: Topic :: Utilities
Requires-Python: >=3.6
License-File: LICENSE.txt
Requires-Dist: paramiko >=2.7.2
